cti_ctf_challenges/__init__.py
cti_ctf_challenges/core.py
cti_ctf_challenges-0.1.2.dist-info/METADATA
cti_ctf_challenges-0.1.2.dist-info/WHEEL
cti_ctf_challenges-0.1.2.dist-info/top_level.txt
cti_ctf_challenges-0.1.2.dist-info/RECORD
